labdrivers/__init__.py
labdrivers/labdrivers.py
labdrivers/version.py
labdrivers/keithley/__init__.py
labdrivers/keithley/k2400.py
labdrivers/keithley/keithley2400.py
labdrivers/lakeshore/__init__.py
labdrivers/lakeshore/ls332.py
labdrivers/ni/__init__.py
labdrivers/ni/nidaq.py
labdrivers/oxford/__init__.py
labdrivers/oxford/ips120.py
labdrivers/oxford/itc503.py
labdrivers/oxford/mercuryips.py
labdrivers/oxford/triton200.py
labdrivers/quantumdesign/__init__.py
labdrivers/quantumdesign/dynacool.py
labdrivers/quantumdesign/qdinstrument.py
labdrivers/srs/__init__.py
labdrivers/srs/sr830.py
labdrivers-0.9.6.dev0.dist-info/METADATA
labdrivers-0.9.6.dev0.dist-info/RECORD
labdrivers-0.9.6.dev0.dist-info/WHEEL
labdrivers-0.9.6.dev0.dist-info/top_level.txt
