Metadata-Version: 2.1
Name: labdrivers
Version: 0.9.6.dev0
Summary: labdrivers: python drivers for lab instruments
Home-page: http://github.com/masonlab/labdrivers
Author: Henry Hinnefeld
Author-email: henry.hinnefeld@gmail.com
Maintainer: Jeff Damasco
Maintainer-email: jeffdamasco@gmail.com
License: MIT
Platform: OS Independent
Classifier: Development Status :: 3 - Alpha
Classifier: Environment :: Console
Classifier: Intended Audience :: Science/Research
Classifier: License :: OSI Approved :: MIT License
Classifier: Operating System :: OS Independent
Classifier: Programming Language :: Python
Classifier: Topic :: Scientific/Engineering
Requires-Dist: pyvisa
Requires-Dist: PyDAQmx
